Products.i18ntestcase-1.4.0-py2.7-nspkg.pth
Products/i18ntestcase/I18NTestCase.py
Products/i18ntestcase/PoTestCase.py
Products/i18ntestcase/PotTestCase.py
Products/i18ntestcase/VERSION.txt
Products/i18ntestcase/__init__.py
Products/i18ntestcase/framework.py
Products/i18ntestcase/runalltests.py
Products/i18ntestcase/test_i18n.py
Products.i18ntestcase-1.4.0.dist-info/DESCRIPTION.rst
Products.i18ntestcase-1.4.0.dist-info/METADATA
Products.i18ntestcase-1.4.0.dist-info/RECORD
Products.i18ntestcase-1.4.0.dist-info/WHEEL
Products.i18ntestcase-1.4.0.dist-info/metadata.json
Products.i18ntestcase-1.4.0.dist-info/namespace_packages.txt
Products.i18ntestcase-1.4.0.dist-info/top_level.txt
