Metadata-Version: 2.0
Name: Products.i18ntestcase
Version: 1.4.0
Summary: Products.i18ntestcase is build on top of the ZopeTestCase package. It has been developed to simplify testing of gettext i18n files for Zope products.
Home-page: https://github.com/plone/Products.i18ntestcase
Author: Hanno Schlichting
Author-email: plone-developers@lists.sourceforge.net
License: GPL
Keywords: Plone i18n gettext testcase
Platform: UNKNOWN
Classifier: Framework :: Plone
Classifier: Framework :: Plone :: 4.3
Classifier: Framework :: Plone :: 5.0
Classifier: Framework :: Zope2
Classifier: License :: OSI Approved :: GNU General Public License (GPL)
Classifier: Programming Language :: Python
Classifier: Programming Language :: Python :: 2.6
Classifier: Programming Language :: Python :: 2.7
Requires-Dist: setuptools
Requires-Dist: six
